MANIFEST.in
README.md
setup.py
hehey_hrouter.egg-info/PKG-INFO
hehey_hrouter.egg-info/SOURCES.txt
hehey_hrouter.egg-info/dependency_links.txt
hehey_hrouter.egg-info/top_level.txt
hrouter/README.md
hrouter/__init__.py
hrouter/route.py
hrouter/base/BaseRouter.py
hrouter/base/RouterRequest.py
hrouter/base/Rule.py
hrouter/base/__init__.py
hrouter/easy/EasyRouter.py
hrouter/easy/EasyRule.py
hrouter/easy/__init__.py
hrouter/utils/RouteUtil.py
hrouter/utils/__init__.py