Metadata-Version: 2.1
Name: hehey-hrouter
Version: 1.0.1
Summary: hehey-hrouter 是一个python 路由工具组件,仿Yii2 路由规则
Home-page: https://gitee.com/chinahehe/hehey-hrouter
Author: 13564768842
Author-email: chinabluexfw@163.com
License: UNKNOWN
Platform: UNKNOWN
